corflow/Transcription.py
corflow/__init__.py
corflow/fromElan.py
corflow/fromExmaralda.py
corflow/fromPangloss.py
corflow/fromPraat.py
corflow/fromTranscriber.py
corflow/toElan.py
corflow/toExmaralda.py
corflow/toPangloss.py
corflow/toPraat.py
corflow/toTEI.py
corflow/toTranscriber.py
corflow-3.4.3.dist-info/licenses/LICENSE
corflow-3.4.3.dist-info/METADATA
corflow-3.4.3.dist-info/WHEEL
corflow-3.4.3.dist-info/top_level.txt
corflow-3.4.3.dist-info/RECORD
