Metadata-Version: 2.4
Name: corflow
Version: 3.4.3
Summary: A conversion/manipulation tool for oral linguistics.
Author-email: François Delafontaine <francois.delafontaine@unine.ch>, Aleksandr Schamberger <schamberger@leibniz-zas.de>
License: CC-BY-4.0
Project-URL: repository, https://github.com/DoReCo/corflow
Classifier: Development Status :: 5 - Production/Stable
Classifier: Intended Audience :: Science/Research
Classifier: Operating System :: Microsoft :: Windows
Classifier: Natural Language :: English
Classifier: Programming Language :: Python :: 3
Classifier: Topic :: Scientific/Engineering
Requires-Python: >=3.10
License-File: LICENSE
Dynamic: license-file
